_x52.cp38-win_amd64.pyd
x52/DirectOutput.dll
x52/__init__.py
x52-0.0.5.dist-info/LICENSE
x52-0.0.5.dist-info/METADATA
x52-0.0.5.dist-info/WHEEL
x52-0.0.5.dist-info/top_level.txt
x52-0.0.5.dist-info/RECORD
