Metadata-Version: 2.1
Name: x52
Version: 0.0.5
Summary: A simple to use package to utilize the MFD on the Throttle of the X52 and X52 Pro.
Home-page: https://github.com/raflchan/x52-py
Author: rafl
License: UNKNOWN
Platform: UNKNOWN
Classifier: Programming Language :: Python :: 3
Classifier: License :: OSI Approved :: MIT License
Classifier: Operating System :: Microsoft :: Windows
Requires-Python: >=3.6
